TranscriptSampler/__init__.py
TranscriptSampler/cli.py
TranscriptSampler/helper_functions.py
TranscriptSampler/transcript_sampler.py
TranscriptSampler-0.0.15.dist-info/LICENSE.md
TranscriptSampler-0.0.15.dist-info/METADATA
TranscriptSampler-0.0.15.dist-info/WHEEL
TranscriptSampler-0.0.15.dist-info/entry_points.txt
TranscriptSampler-0.0.15.dist-info/top_level.txt
TranscriptSampler-0.0.15.dist-info/RECORD
