Metadata-Version: 2.1
Name: TranscriptSampler
Version: 0.0.15
Summary: sample transcripts
Home-page: https://gitlab.com/noepozzan/programming-life-sciences.git
Author: Noè Pozzan
Author-email: noe.pozzan@stud.unibas.ch
License: MIT
Platform: UNKNOWN
License-File: LICENSE.md
Requires-Dist: click
